README.md
pyproject.toml
setup.py
mongodb_toolbox/__init__.py
mongodb_toolbox/py.typed
mongodb_toolbox/toolbox.py
mongodb_toolbox.egg-info/PKG-INFO
mongodb_toolbox.egg-info/SOURCES.txt
mongodb_toolbox.egg-info/dependency_links.txt
mongodb_toolbox.egg-info/requires.txt
mongodb_toolbox.egg-info/top_level.txt